{
  "main": {
    "id": "94254b9dc19765d4",
    "type": "split",
    "children": [
      {
        "id": "dc1a96779f46adff",
        "type": "tabs",
        "children": [
          {
            "id": "ce171009820e25b5",
            "type": "leaf",
            "state": {
              "type": "markdown",
              "state": {
                "file": "manual/Nvim_setup.md",
                "mode": "preview",
                "source": true
              }
            }
          }
        ]
      }
    ],
    "direction": "vertical"
  },
  "left": {
    "id": "6b5e02816aee20ff",
    "type": "mobile-drawer",
    "children": [
      {
        "id": "93f9916d4ee0bc8f",
        "type": "leaf",
        "state": {
          "type": "file-explorer",
          "state": {
            "sortOrder": "alphabetical"
          }
        }
      },
      {
        "id": "fadb4029ceafa891",
        "type": "leaf",
        "state": {
          "type": "search",
          "state": {
            "query": "",
            "matchingCase": false,
            "explainSearch": false,
            "collapseAll": false,
            "extraContext": false,
            "sortOrder": "alphabetical"
          }
        }
      },
      {
        "id": "98a087301f2452cd",
        "type": "leaf",
        "state": {
          "type": "tag",
          "state": {
            "sortOrder": "frequency",
            "useHierarchy": true
          }
        }
      },
      {
        "id": "968ccf5c5fe71910",
        "type": "leaf",
        "state": {
          "type": "starred",
          "state": {}
        }
      }
    ]
  },
  "right": {
    "id": "917a24340ae3843e",
    "type": "mobile-drawer",
    "children": [
      {
        "id": "e1bc9145a3035e46",
        "type": "leaf",
        "state": {
          "type": "backlink",
          "state": {
            "file": "manual/Nvim_setup.md",
            "collapseAll": false,
            "extraContext": false,
            "sortOrder": "alphabetical",
            "showSearch": false,
            "searchQuery": "",
            "backlinkCollapsed": false,
            "unlinkedCollapsed": true
          }
        }
      },
      {
        "id": "9bc888c0275465ce",
        "type": "leaf",
        "state": {
          "type": "outgoing-link",
          "state": {
            "file": "manual/Nvim_setup.md",
            "linksCollapsed": false,
            "unlinkedCollapsed": true
          }
        }
      },
      {
        "id": "4c9cd1ec52cf442f",
        "type": "leaf",
        "state": {
          "type": "outline",
          "state": {
            "file": "manual/Nvim_setup.md"
          }
        }
      }
    ],
    "currentTab": 0
  },
  "active": "ce171009820e25b5",
  "lastOpenFiles": [
    "diary/2022-12-31.md",
    "manual/Nvim_setup.md",
    "manual/latex.md",
    "manual/Note-Taking.md",
    "diary/2022-12-30.md"
  ]
}